{"l":[{"d":"Tisch","f":1045,"x":false,"a":["Tische","Tisch","Waldtisch","Holztisch","Table"]},{"d":"Stuhl","f":786,"x":false,"a":["Stühle","Stuhl","Chair","Stuhle"]},{"d":"Baum","f":676,"x":false,"a":["Bäume","Baum"]},{"d":"Schrank","f":526,"x":false,"a":["Schränke","Schrank"]},{"d":"Dildo","f":359,"x":true,"a":["Dildo"]},{"d":"Haus","f":328,"x":false,"a":["Häuser","Haus"]},{"d":"Brett","f":318,"x":false,"a":["Bretter","Brett","Holzbrett"]},{"d":"Tür","f":309,"x":false,"a":["Tuer","Tür","Türen"]},{"d":"Bett","f":306,"x":false,"a":["Bett"]},{"d":"Regal","f":260,"x":false,"a":["Regale","Regal"]},{"d":"Holz","f":216,"x":false,"a":["Holz"]},{"d":"Boden","f":215,"x":false,"a":["Boden"]},{"d":"Löffel","f":191,"x":false,"a":["Löffel"]},{"d":"Bank","f":177,"x":false,"a":["Bank"]},{"d":"Papier","f":164,"x":false,"a":["Papier"]},{"d":"Spielzeug","f":154,"x":false,"a":["Spielzeug"]},{"d":"Auto","f":146,"x":false,"a":["Auto"]},{"d":"Wand","f":141,"x":false,"a":["Wand"]},{"d":"Messer","f":129,"x":false,"a":["Messer"]},{"d":"Ast","f":121,"x":false,"a":["Ast"]},{"d":"Fenster","f":117,"x":false,"a":["Fenster"]},{"d":"Zaun","f":116,"x":false,"a":["Zaun"]},{"d":"Möbel","f":115,"x":false,"a":["Möbel"]},{"d":"Stock","f":114,"x":false,"a":["Stock"]},{"d":"Gabel","f":114,"x":false,"a":["Gabel"]},{"d":"Schuh","f":111,"x":false,"a":["Schuhe","Schuh"]},{"d":"Lampe","f":107,"x":false,"a":["Lampe"]},{"d":"Kopf","f":105,"x":false,"a":["Kopf"]},{"d":"Kiste","f":105,"x":false,"a":["Kiste"]},{"d":"Dach","f":103,"x":false,"a":["Dach"]},{"d":"Bein","f":98,"x":false,"a":["Bein"]},{"d":"Hütte","f":98,"x":false,"a":["Hüte","Hütte"]},{"d":"Puppe","f":98,"x":false,"a":["Puppe"]},{"d":"Teller","f":97,"x":false,"a":["Teller"]},{"d":"Stift","f":97,"x":false,"a":["Stift"]},{"d":"Boot","f":95,"x":false,"a":["Boote","Boot"]},{"d":"Kommode","f":88,"x":false,"a":["Komode","Kommode"]},{"d":"Uhr","f":85,"x":false,"a":["Uhr"]},{"d":"Decke","f":81,"x":false,"a":["Decke"]},{"d":"Kochlöffel","f":75,"x":false,"a":["Kochlöffel"]},{"d":"Figur","f":74,"x":false,"a":["Figur"]},{"d":"Balken","f":74,"x":false,"a":["Balken"]},{"d":"Hammer","f":73,"x":false,"a":["Hammer"]},{"d":"Pinocchio","f":72,"x":false,"a":["Pinocchio"]},{"d":"Schaukelpferd","f":72,"x":false,"a":["Pferd","Schaukelpferd"]},{"d":"Schreibtisch","f":71,"x":false,"a":["Schreibtisch"]},{"d":"Besteck","f":71,"x":false,"a":["Besteck"]},{"d":"Rahmen","f":70,"x":false,"a":["Rahmen"]},{"d":"Parkett","f":69,"x":false,"a":["Parkett"]},{"d":"Leiter","f":66,"x":false,"a":["Leiter"]},{"d":"Schiff","f":64,"x":false,"a":["Schiff"]},{"d":"Schüssel","f":61,"x":false,"a":["Schüssel"]},{"d":"Gitarre","f":61,"x":false,"a":["Gitarren","Gitarre"]},{"d":"Buch","f":61,"x":false,"a":["Buch"]},{"d":"Baumstamm","f":60,"x":false,"a":["Stamm","Baumstamm"]},{"d":"Becher","f":58,"x":false,"a":["Becher"]},{"d":"Bilderrahmen","f":57,"x":false,"a":["Bilderrahmen"]},{"d":"Zahnstocher","f":56,"x":false,"a":["Zahnstocher"]},{"d":"Treppe","f":56,"x":false,"a":["Treppe"]},{"d":"Brennholz","f":56,"x":false,"a":["Brennmaterial","Brennholz","Lagerfeuer"]},{"d":"Flöte","f":55,"x":false,"a":["Flöte"]},{"d":"Hocker","f":55,"x":false,"a":["Hocker"]},{"d":"Tasse","f":55,"x":false,"a":["Tasse"]},{"d":"Axt","f":53,"x":false,"a":["Axt"]},{"d":"Rad","f":51,"x":false,"a":["Rad"]},{"d":"Feuerholz","f":50,"x":false,"a":["Feuer","Feuerholz"]},{"d":"Toilette","f":50,"x":false,"a":["Klo","Toilette"]},{"d":"Geige","f":49,"x":false,"a":["Geige"]},{"d":"Sessel","f":49,"x":false,"a":["Sessel"]},{"d":"Küche","f":48,"x":false,"a":["Kueche","Küche"]},{"d":"Wald","f":47,"x":false,"a":["Wald"]},{"d":"Klavier","f":47,"x":false,"a":["Klavier"]},{"d":"Baumhaus","f":47,"x":false,"a":["Baumhaus"]},{"d":"Laminat","f":47,"x":false,"a":["Laminat"]},{"d":"Fahrrad","f":45,"x":false,"a":["Fahrrad"]},{"d":"Platte","f":44,"x":false,"a":["Platte"]},{"d":"Schwert","f":44,"x":false,"a":["Schwert"]},{"d":"Streichholz","f":43,"x":false,"a":["Streichholz"]},{"d":"Kasten","f":43,"x":false,"a":["Kasten"]},{"d":"Vogelhaus","f":42,"x":false,"a":["Vogelhaus"]},{"d":"Werkzeug","f":42,"x":false,"a":["Werkzeug"]},{"d":"Fass","f":40,"x":false,"a":["Fass"]},{"d":"Sofa","f":40,"x":false,"a":["Sofa"]},{"d":"Flasche","f":40,"x":false,"a":["Flasche"]},{"d":"Schneidebrett","f":38,"x":false,"a":["Schneidebrett"]},{"d":"Box","f":38,"x":false,"a":["Box"]},{"d":"Bogen","f":38,"x":false,"a":["Bogen"]},{"d":"Truhe","f":37,"x":false,"a":["Truhe"]},{"d":"Baseballschläger","f":36,"x":false,"a":["Baseballschläger"]},{"d":"Latte","f":36,"x":false,"a":["Latten","Latte"]},{"d":"Schale","f":36,"x":false,"a":["Schalle","Schale"]},{"d":"Dekoration","f":35,"x":false,"a":["Deko","Dekoration"]},{"d":"Besen","f":35,"x":false,"a":["Besen"]},{"d":"Brücke","f":34,"x":false,"a":["Brücke"]},{"d":"Bleistift","f":34,"x":false,"a":["Bleistift"]},{"d":"Topf","f":34,"x":false,"a":["Topf"]},{"d":"Eiche","f":34,"x":false,"a":["Eiche"]},{"d":"Bild","f":34,"x":false,"a":["Bild"]},{"d":"Schaukel","f":32,"x":false,"a":["Schaukel"]},{"d":"Essen","f":31,"x":false,"a":["Essen"]},{"d":"Kugel","f":30,"x":false,"a":["Kugel"]},{"d":"Griff","f":29,"x":false,"a":["Griff"]},{"d":"Karton","f":29,"x":false,"a":["Karton"]},{"d":"Glas","f":29,"x":false,"a":["Glas"]},{"d":"Pappe","f":29,"x":false,"a":["Pappe"]},{"d":"Tier","f":28,"x":false,"a":["Tier"]},{"d":"Penis","f":28,"x":true,"a":["Penis"]},{"d":"Schläger","f":27,"x":false,"a":["Schläger"]},{"d":"Schaufel","f":27,"x":false,"a":["Schaufel"]},{"d":"Würfel","f":27,"x":false,"a":["Würfel"]},{"d":"Brille","f":27,"x":false,"a":["Brille"]},{"d":"Schach","f":27,"x":false,"a":["Schach"]},{"d":"Schublade","f":27,"x":false,"a":["Schublade"]},{"d":"Schild","f":27,"x":false,"a":["Schild"]},{"d":"Auge","f":27,"x":false,"a":["Auge"]},{"d":"Computer","f":26,"x":false,"a":["Computer"]},{"d":"Eimer","f":26,"x":false,"a":["Eimer"]},{"d":"Tor","f":25,"x":false,"a":["Tor"]},{"d":"Pfeil","f":25,"x":false,"a":["Pfeil"]},{"d":"Säge","f":25,"x":false,"a":["Säge"]},{"d":"Pflanze","f":25,"x":false,"a":["Pflanze"]},{"d":"Blatt","f":25,"x":false,"a":["Blatt"]},{"d":"Handy","f":25,"x":false,"a":["Handy"]},{"d":"Stab","f":25,"x":false,"a":["Stab"]},{"d":"Fußboden","f":24,"x":false,"a":["Fussboden","Fußboden"]},{"d":"Stein","f":24,"x":false,"a":["Stein"]},{"d":"Ball","f":24,"x":false,"a":["Ball"]},{"d":"Korb","f":24,"x":false,"a":["Korb"]},{"d":"Flugzeug","f":24,"x":false,"a":["Flugzeug"]},{"d":"Steg","f":23,"x":false,"a":["Steg"]},{"d":"Zahnbürste","f":23,"x":false,"a":["Zahnbürste"]},{"d":"Vase","f":23,"x":false,"a":["Vase"]},{"d":"Ofen","f":23,"x":false,"a":["Ofen"]},{"d":"Birke","f":23,"x":false,"a":["Birke"]},{"d":"Zug","f":23,"x":false,"a":["Zug"]},{"d":"Holzbein","f":22,"x":false,"a":["Holzbein"]},{"d":"Schuppen","f":22,"x":false,"a":["Schuppen"]},{"d":"Zweig","f":22,"x":false,"a":["Zweig"]},{"d":"Statue","f":22,"x":false,"a":["Statue"]},{"d":"Planke","f":22,"x":false,"a":["Planke"]},{"d":"Spiel","f":22,"x":false,"a":["Spiel"]},{"d":"Tanne","f":22,"x":false,"a":["Tanne"]},{"d":"Arm","f":22,"x":false,"a":["Arm"]},{"d":"Klotz","f":21,"x":false,"a":["Klotz"]},{"d":"Tafel","f":20,"x":false,"a":["Tafel"]},{"d":"Kleiderschrank","f":20,"x":false,"a":["Kleiderschrank"]},{"d":"Nussknacker","f":20,"x":false,"a":["Nussknacker"]},{"d":"Schlitten","f":19,"x":false,"a":["Schlitten"]},{"d":"Eisenbahn","f":19,"x":false,"a":["Eisenbahn"]},{"d":"Hund","f":19,"x":false,"a":["Hund"]},{"d":"Gartenhaus","f":18,"x":false,"a":["Gartenhaus"]},{"d":"Kohle","f":18,"x":false,"a":["Kohle"]},{"d":"Weg","f":18,"x":false,"a":["Weg"]},{"d":"Lattenrost","f":17,"x":false,"a":["Lattenrost"]},{"d":"Kanu","f":17,"x":false,"a":["Kanu"]},{"d":"Figuren","f":15,"x":false,"a":["Figuren"]},{"d":"Brettchen","f":14,"x":false,"a":["Brettchen"]},{"d":"Beil","f":14,"x":false,"a":["Beil"]},{"d":"Holzlöffel","f":14,"x":false,"a":["Holzlöffel"]},{"d":"Kreuz","f":14,"x":false,"a":["Kreuz"]},{"d":"Fensterrahmen","f":13,"x":false,"a":["Fensterrahmen"]},{"d":"Stall","f":13,"x":false,"a":["Stall"]},{"d":"Hundehütte","f":13,"x":false,"a":["Hundehütte"]},{"d":"Wurzel","f":12,"x":false,"a":["Wurzel"]},{"d":"Schaukelstuhl","f":12,"x":false,"a":["Schaukelstuhl"]},{"d":"Ring","f":12,"x":false,"a":["Ring"]},{"d":"Turm","f":12,"x":false,"a":["Turm"]},{"d":"Sideboard","f":12,"x":false,"a":["Sideboard"]},{"d":"Balkon","f":12,"x":false,"a":["Balkon"]},{"d":"Dachstuhl","f":11,"x":false,"a":["Dachstuhl"]},{"d":"Wippe","f":11,"x":false,"a":["Wippe"]},{"d":"Anhänger","f":11,"x":false,"a":["Anhänger"]},{"d":"Knopf","f":11,"x":false,"a":["Knopf"]},{"d":"Cello","f":10,"x":false,"a":["Cello"]},{"d":"Carport","f":10,"x":false,"a":["Carport"]},{"d":"Bücherregal","f":10,"x":false,"a":["Bücherregal"]},{"d":"Esstisch","f":9,"x":false,"a":["Esstisch"]},{"d":"Besenstiel","f":9,"x":false,"a":["Besenstiehl","Besenstiel"]},{"d":"Schachtel","f":9,"x":false,"a":["Schachtel"]},{"d":"Essstäbchen","f":9,"x":false,"a":["Essstäbchen"]},{"d":"Sauna","f":8,"x":false,"a":["Sauna"]},{"d":"Tannenbaum","f":8,"x":false,"a":["Tannenbaum"]},{"d":"Arbeitsplatte","f":8,"x":false,"a":["Arbeitsplatte"]},{"d":"Orgel","f":8,"x":false,"a":["Orgel"]},{"d":"Blockflöte","f":8,"x":false,"a":["Blockflöte"]},{"d":"Gehstock","f":7,"x":false,"a":["Gehstock"]},{"d":"Instrumente","f":7,"x":false,"a":["Instrumente"]},{"d":"Klettergerüst","f":7,"x":false,"a":["Klettergerüst"]},{"d":"Skateboard","f":6,"x":false,"a":["Skateboard"]},{"d":"Holzkiste","f":6,"x":false,"a":["Holzkiste"]},{"d":"Tischplatte","f":6,"x":false,"a":["Tischplatte"]},{"d":"Karre","f":6,"x":false,"a":["Karre"]},{"d":"Holzspielzeug","f":5,"x":false,"a":["Holzspielzeug"]},{"d":"Schneidbrett","f":5,"x":false,"a":["Schneidbrett"]},{"d":"Holzhaus","f":5,"x":false,"a":["Holzhaus"]},{"d":"Flur","f":5,"x":false,"a":["Flur"]},{"d":"Holzpferd","f":5,"x":false,"a":["Holzpferd"]},{"d":"Kuckucksuhr","f":5,"x":false,"a":["Kuckucksuhr"]},{"d":"Span","f":5,"x":false,"a":["Span"]},{"d":"Gartenzaun","f":4,"x":false,"a":["Gartenzaun"]},{"d":"Sekretär","f":3,"x":false,"a":["Sekretär"]},{"d":"Fachwerk","f":3,"x":false,"a":["Fachwerk"]},{"d":"Obstschale","f":3,"x":false,"a":["Obstschale"]},{"d":"Bierbank","f":3,"x":false,"a":["Bierbank"]},{"d":"Suppenlöffel","f":3,"x":false,"a":["Suppenlöffel"]},{"d":"Fach","f":3,"x":false,"a":["Fach"]},{"d":"Stifte","f":3,"x":false,"a":["Stifte"]},{"d":"Totem","f":2,"x":false,"a":["Totem"]},{"d":"Holzstuhl","f":2,"x":false,"a":["Holzstuhl"]},{"d":"Sitzbank","f":2,"x":false,"a":["Sitzbank"]},{"d":"Mörser","f":2,"x":false,"a":["Mörser"]},{"d":"Holztreppe","f":2,"x":false,"a":["Holztreppe"]},{"d":"Hölzern","f":2,"x":false,"a":["Hölzern"]},{"d":"Hobelbank","f":2,"x":false,"a":["Hobelbank"]},{"d":"Vogelhäuschen","f":2,"x":false,"a":["Vogelhäuschen"]},{"d":"Holzschnitzerei","f":2,"x":false,"a":["Holzschnitzerei"]},{"d":"Schachspiel","f":2,"x":false,"a":["Schachspiel"]},{"d":"Bettgestell","f":2,"x":false,"a":["Bettgestell"]},{"d":"Schiffe","f":2,"x":false,"a":["Schiffe"]},{"d":"Holzeisenbahn","f":2,"x":false,"a":["Holzeisenbahn"]},{"d":"Nachtschrank","f":2,"x":false,"a":["Nachtschrank"]},{"d":"Axtstiel","f":2,"x":false,"a":["Axtstiel"]},{"d":"Dächer","f":2,"x":false,"a":["Dächer"]},{"d":"Küchentisch","f":2,"x":false,"a":["Küchentisch"]},{"d":"Dielenboden","f":1,"x":false,"a":["Dielenboden"]},{"d":"Himmelbett","f":1,"x":false,"a":["Himmelbett"]},{"d":"Axtgriff","f":1,"x":false,"a":["Axtgriff"]},{"d":"Holzregal","f":1,"x":false,"a":["Holzregal"]},{"d":"Hochstand","f":1,"x":false,"a":["Hochstand"]},{"d":"Fachwerkbalken","f":1,"x":false,"a":["Fachwerkbalken"]},{"d":"Regalbretter","f":1,"x":false,"a":["Regalbretter"]},{"d":"Baumhäuser","f":1,"x":false,"a":["Baumhäuser"]},{"d":"Geigen","f":1,"x":false,"a":["Geigen"]},{"d":"Pinocciosnase","f":1,"x":false,"a":["Pinocciosnase"]},{"d":"Segelmast","f":1,"x":false,"a":["Segelmast"]},{"d":"Fotorahmen","f":1,"x":false,"a":["Fotorahmen"]},{"d":"Zündholz","f":1,"x":false,"a":["Zündholz"]},{"d":"Brücken","f":1,"x":false,"a":["Brücken"]},{"d":"Schnitzereien","f":1,"x":false,"a":["Schnitzereien"]},{"d":"Sculpture","f":1,"x":false,"a":["Sculpture"]},{"d":"Astgabel","f":1,"x":false,"a":["Astgabel"]},{"d":"Holzwerk","f":1,"x":false,"a":["Holzwerk"]},{"d":"Wagenrad","f":1,"x":false,"a":["Wagenrad"]},{"d":"Massagestäbe","f":1,"x":false,"a":["Massagestäbe"]},{"d":"Blockbohlenhaus","f":1,"x":false,"a":["Blockbohlenhaus"]},{"d":"Kaminscheit","f":1,"x":false,"a":["Kaminscheit"]},{"d":"Schwedenhaus","f":1,"x":false,"a":["Schwedenhaus"]}]}