{"l":[{"d":"eat","f":93,"x":false,"a":["eating","eat"]},{"d":"walk","f":87,"x":false,"a":["walked","walk","walking"]},{"d":"sleep","f":68,"x":false,"a":["sleeping","sleep"]},{"d":"work","f":32,"x":false,"a":["working","work"]},{"d":"run","f":30,"x":false,"a":["running","run","jog","ran"]},{"d":"talk","f":26,"x":false,"a":["speak","talk","talking","converse","chat"]},{"d":"breathe","f":24,"x":false,"a":["breathing","breathe"]},{"d":"drive","f":22,"x":false,"a":["driving","drive"]},{"d":"drink","f":18,"x":true,"a":["drink"]},{"d":"poop","f":15,"x":false,"a":["shit","poop","pooping"]},{"d":"read","f":13,"x":false,"a":["reading","read"]},{"d":"wake","f":13,"x":false,"a":["woke","wake"]},{"d":"shower","f":12,"x":false,"a":["shower"]},{"d":"clean","f":12,"x":false,"a":["cleaning","clean"]},{"d":"see","f":11,"x":false,"a":["peer","see","look"]},{"d":"brush","f":10,"x":false,"a":["brush"]},{"d":"cook","f":10,"x":false,"a":["cooked","cook"]},{"d":"wash","f":9,"x":false,"a":["washing","wash"]},{"d":"sit","f":9,"x":false,"a":["sitting","sit"]},{"d":"binge","f":8,"x":false,"a":["binge"]},{"d":"jump","f":8,"x":false,"a":["jump"]},{"d":"pee","f":8,"x":false,"a":["pee"]},{"d":"watch","f":7,"x":false,"a":["watch"]},{"d":"smile","f":7,"x":false,"a":["smile"]},{"d":"think","f":7,"x":false,"a":["think"]},{"d":"blink","f":7,"x":false,"a":["blink"]},{"d":"complain","f":6,"x":false,"a":["complain"]},{"d":"belch","f":6,"x":false,"a":["burp","belch"]},{"d":"stand","f":6,"x":false,"a":["stand"]},{"d":"surf","f":6,"x":false,"a":["surf"]},{"d":"caffeinate","f":6,"x":false,"a":["caffeinate"]},{"d":"fart","f":6,"x":false,"a":["fart"]},{"d":"yawn","f":6,"x":false,"a":["yawn"]},{"d":"smoke","f":5,"x":true,"a":["smoke"]},{"d":"swim","f":5,"x":false,"a":["swim"]},{"d":"energize","f":5,"x":false,"a":["energize"]},{"d":"juggle","f":5,"x":false,"a":["juggle"]},{"d":"laugh","f":5,"x":false,"a":["laugh"]},{"d":"dance","f":5,"x":false,"a":["dance"]},{"d":"sing","f":5,"x":false,"a":["sing"]},{"d":"procrastinate","f":5,"x":false,"a":["procrastinate"]},{"d":"exercise","f":5,"x":false,"a":["exercising","exercise"]},{"d":"overthink","f":5,"x":false,"a":["overthink"]},{"d":"stream","f":5,"x":false,"a":["stream"]},{"d":"ride","f":5,"x":false,"a":["ride"]},{"d":"nap","f":5,"x":false,"a":["doze","nap"]},{"d":"xerox","f":5,"x":false,"a":["duplicate","xerox"]},{"d":"banter","f":5,"x":false,"a":["banter"]},{"d":"adulting","f":5,"x":false,"a":["adulting"]},{"d":"relax","f":5,"x":false,"a":["relax"]},{"d":"hear","f":5,"x":false,"a":["hear"]},{"d":"rant","f":5,"x":false,"a":["rant"]},{"d":"type","f":5,"x":false,"a":["typing","type"]},{"d":"meme","f":4,"x":false,"a":["meme"]},{"d":"play","f":4,"x":false,"a":["play"]},{"d":"bathe","f":4,"x":false,"a":["bathe"]},{"d":"influencer","f":4,"x":false,"a":["influencer"]},{"d":"scream","f":4,"x":false,"a":["scream"]},{"d":"promote","f":4,"x":false,"a":["promote"]},{"d":"indulge","f":4,"x":false,"a":["indulge"]},{"d":"write","f":4,"x":false,"a":["write"]},{"d":"share","f":4,"x":false,"a":["share"]},{"d":"hustle","f":4,"x":false,"a":["hustle"]},{"d":"cope","f":4,"x":false,"a":["cope"]},{"d":"selfie","f":4,"x":false,"a":["selfie"]},{"d":"kondo","f":4,"x":false,"a":["kondo"]},{"d":"grind","f":4,"x":false,"a":["grind"]},{"d":"study","f":4,"x":false,"a":["studying","study"]},{"d":"post","f":4,"x":false,"a":["post"]},{"d":"uber","f":4,"x":false,"a":["uber"]},{"d":"grumble","f":4,"x":false,"a":["grumble"]},{"d":"hashtag","f":4,"x":false,"a":["hashtag"]},{"d":"zoom","f":4,"x":false,"a":["zoom"]},{"d":"emoji","f":4,"x":false,"a":["emoji"]},{"d":"browse","f":4,"x":false,"a":["browse"]},{"d":"vape","f":4,"x":true,"a":["vape"]},{"d":"netflix","f":4,"x":false,"a":["netflix"]},{"d":"throw","f":4,"x":false,"a":["throw"]},{"d":"travel","f":4,"x":false,"a":["travel"]},{"d":"troll","f":4,"x":false,"a":["troll"]},{"d":"manage","f":4,"x":false,"a":["manage"]},{"d":"stretch","f":4,"x":false,"a":["stretch"]},{"d":"provoke","f":4,"x":false,"a":["provoke"]},{"d":"vent","f":4,"x":false,"a":["vent"]},{"d":"balance","f":4,"x":false,"a":["balance"]},{"d":"react","f":4,"x":false,"a":["react"]},{"d":"puff","f":4,"x":true,"a":["puff"]},{"d":"delay","f":4,"x":false,"a":["delay"]},{"d":"joke","f":3,"x":false,"a":["joke"]},{"d":"tag","f":3,"x":false,"a":["tag"]},{"d":"inhale","f":3,"x":false,"a":["inhale"]},{"d":"videochat","f":3,"x":false,"a":["videochat"]},{"d":"doomscroll","f":3,"x":false,"a":["doomscroll"]},{"d":"grin","f":3,"x":false,"a":["grin"]},{"d":"multitask","f":3,"x":false,"a":["multitask"]},{"d":"gorge","f":3,"x":false,"a":["gorge"]},{"d":"waddle","f":3,"x":false,"a":["waddle"]},{"d":"move","f":3,"x":false,"a":["move"]},{"d":"copy","f":3,"x":false,"a":["copy"]},{"d":"tidy","f":3,"x":false,"a":["tidy"]},{"d":"spread","f":3,"x":false,"a":["spread"]},{"d":"piss","f":3,"x":true,"a":["piss"]},{"d":"snooze","f":3,"x":false,"a":["snooze"]},{"d":"aware","f":3,"x":false,"a":["aware"]},{"d":"yeet","f":3,"x":false,"a":["yeet"]},{"d":"dress","f":3,"x":false,"a":["dress"]},{"d":"fangirl","f":3,"x":false,"a":["fangirl"]},{"d":"ramble","f":3,"x":false,"a":["ramble"]},{"d":"quarantine","f":3,"x":false,"a":["quarantine"]},{"d":"munch","f":3,"x":false,"a":["munch"]},{"d":"adore","f":3,"x":false,"a":["adore"]},{"d":"devour","f":3,"x":false,"a":["devour"]},{"d":"commute","f":3,"x":false,"a":["commute"]},{"d":"wander","f":3,"x":false,"a":["meander","wander","amble"]},{"d":"daydream","f":3,"x":false,"a":["daydream"]},{"d":"postpone","f":3,"x":false,"a":["postpone"]},{"d":"isolate","f":3,"x":false,"a":["isolate"]},{"d":"wobble","f":3,"x":false,"a":["wobble"]},{"d":"organize","f":3,"x":false,"a":["organize"]},{"d":"ignored","f":3,"x":false,"a":["ignored"]},{"d":"toddle","f":3,"x":false,"a":["toddle"]},{"d":"ghosted","f":3,"x":false,"a":["ghosted"]},{"d":"declutter","f":3,"x":false,"a":["declutter"]},{"d":"ponder","f":3,"x":false,"a":["ponder"]},{"d":"lurk","f":3,"x":false,"a":["lurk"]},{"d":"wink","f":3,"x":false,"a":["wink"]},{"d":"obsess","f":3,"x":false,"a":["obsess"]},{"d":"slouch","f":3,"x":false,"a":["slouch"]},{"d":"fiddle","f":2,"x":false,"a":["fiddle"]},{"d":"fumble","f":2,"x":false,"a":["fumble"]},{"d":"snap","f":2,"x":false,"a":["snap"]},{"d":"sketch","f":2,"x":false,"a":["sketch"]},{"d":"squint","f":2,"x":false,"a":["squint"]},{"d":"photograph","f":2,"x":false,"a":["photograph"]},{"d":"whinge","f":2,"x":false,"a":["whinge"]},{"d":"strive","f":2,"x":false,"a":["strive"]},{"d":"facepalm","f":2,"x":false,"a":["facepalm"]},{"d":"slay","f":2,"x":false,"a":["slay"]},{"d":"sip","f":2,"x":false,"a":["sip"]},{"d":"stimulate","f":2,"x":false,"a":["stimulate"]},{"d":"dash","f":2,"x":false,"a":["dash"]},{"d":"pout","f":2,"x":false,"a":["pout"]},{"d":"strut","f":2,"x":false,"a":["strut"]},{"d":"nibble","f":2,"x":false,"a":["nibble"]},{"d":"perk","f":2,"x":false,"a":["perk"]},{"d":"live","f":2,"x":false,"a":["live"]},{"d":"imagine","f":2,"x":false,"a":["imagine"]},{"d":"guzzle","f":2,"x":false,"a":["guzzle"]},{"d":"struggle","f":2,"x":false,"a":["struggle"]},{"d":"lounge","f":2,"x":false,"a":["lounge"]},{"d":"analyze","f":2,"x":false,"a":["analyze"]},{"d":"waffle","f":2,"x":false,"a":["waffle"]},{"d":"fantasize","f":2,"x":false,"a":["fantasize"]},{"d":"mope","f":2,"x":false,"a":["mope"]},{"d":"separate","f":2,"x":false,"a":["separate"]},{"d":"creep","f":2,"x":false,"a":["creep"]},{"d":"taste","f":2,"x":false,"a":["taste"]},{"d":"doodle","f":2,"x":false,"a":["doodle"]},{"d":"prattle","f":2,"x":false,"a":["prattle"]},{"d":"respond","f":2,"x":false,"a":["respond"]},{"d":"shimmy","f":2,"x":false,"a":["shimmy"]},{"d":"connect","f":2,"x":false,"a":["connect"]},{"d":"chug","f":2,"x":false,"a":["chug"]},{"d":"label","f":2,"x":false,"a":["label"]},{"d":"stumble","f":2,"x":false,"a":["stumble"]},{"d":"toss","f":2,"x":false,"a":["toss"]},{"d":"express","f":2,"x":false,"a":["express"]},{"d":"slump","f":2,"x":false,"a":["slump"]},{"d":"scroll","f":2,"x":false,"a":["scroll"]},{"d":"pose","f":2,"x":false,"a":["pose"]},{"d":"snort","f":2,"x":false,"a":["snort"]},{"d":"cringe","f":2,"x":false,"a":["cringe"]},{"d":"tinker","f":2,"x":false,"a":["tinker"]},{"d":"wince","f":2,"x":false,"a":["wince"]},{"d":"gossip","f":2,"x":false,"a":["gossip"]},{"d":"capture","f":2,"x":false,"a":["capture"]},{"d":"swagger","f":2,"x":false,"a":["swagger"]},{"d":"sulk","f":2,"x":false,"a":["sulk"]},{"d":"drool","f":2,"x":false,"a":["drool"]},{"d":"quip","f":2,"x":false,"a":["quip"]},{"d":"giggle","f":2,"x":false,"a":["giggle"]},{"d":"love","f":2,"x":false,"a":["love"]},{"d":"get","f":2,"x":false,"a":["get"]},{"d":"snack","f":2,"x":false,"a":["snack"]},{"d":"dawdle","f":2,"x":false,"a":["dawdle"]},{"d":"jiggle","f":2,"x":false,"a":["jiggle"]},{"d":"endorse","f":2,"x":false,"a":["endorse"]},{"d":"moan","f":2,"x":false,"a":["moan"]},{"d":"chuckle","f":2,"x":false,"a":["chuckle"]},{"d":"snore","f":2,"x":false,"a":["snore"]},{"d":"ruminate","f":2,"x":false,"a":["ruminate"]},{"d":"sprint","f":2,"x":false,"a":["sprint"]},{"d":"chortle","f":2,"x":false,"a":["chortle"]},{"d":"fidget","f":2,"x":false,"a":["fidget"]},{"d":"fume","f":2,"x":false,"a":["fume"]},{"d":"wiggle","f":2,"x":false,"a":["wiggle"]},{"d":"conscious","f":2,"x":false,"a":["conscious"]},{"d":"take","f":1,"x":false,"a":["take"]},{"d":"vlog","f":1,"x":false,"a":["vlog"]},{"d":"grill","f":1,"x":false,"a":["grill"]},{"d":"contort","f":1,"x":false,"a":["contort"]},{"d":"zen","f":1,"x":false,"a":["zen"]},{"d":"zombify","f":1,"x":false,"a":["zombify"]},{"d":"scribble","f":1,"x":false,"a":["scribble"]},{"d":"lay","f":1,"x":true,"a":["lay"]},{"d":"lollygag","f":1,"x":false,"a":["lollygag"]},{"d":"titter","f":1,"x":false,"a":["titter"]},{"d":"charm","f":1,"x":false,"a":["charm"]},{"d":"yammer","f":1,"x":false,"a":["yammer"]},{"d":"go","f":1,"x":false,"a":["go"]},{"d":"mutter","f":1,"x":false,"a":["mutter"]},{"d":"spoil","f":1,"x":false,"a":["spoil"]},{"d":"worship","f":1,"x":false,"a":["worship"]},{"d":"smirk","f":1,"x":false,"a":["smirk"]},{"d":"stall","f":1,"x":false,"a":["stall"]},{"d":"toil","f":1,"x":false,"a":["toil"]},{"d":"enlightened","f":1,"x":false,"a":["enlightened"]},{"d":"meditate","f":1,"x":false,"a":["meditate"]},{"d":"quaff","f":1,"x":false,"a":["quaff"]},{"d":"improvise","f":1,"x":false,"a":["improvise"]},{"d":"chinwag","f":1,"x":false,"a":["chinwag"]},{"d":"draw","f":1,"x":false,"a":["draw"]},{"d":"gargle","f":1,"x":false,"a":["gargle"]},{"d":"jest","f":1,"x":false,"a":["jest"]},{"d":"abandoned","f":1,"x":false,"a":["abandoned"]},{"d":"journey","f":1,"x":false,"a":["journey"]},{"d":"natter","f":1,"x":false,"a":["natter"]},{"d":"scull","f":1,"x":false,"a":["scull"]},{"d":"karaoke","f":1,"x":false,"a":["karaoke"]},{"d":"graze","f":1,"x":false,"a":["graze"]},{"d":"dribble","f":1,"x":false,"a":["dribble"]},{"d":"scramble","f":1,"x":false,"a":["scramble"]},{"d":"tweet","f":1,"x":false,"a":["tweet"]},{"d":"warble","f":1,"x":false,"a":["warble"]},{"d":"distance","f":1,"x":false,"a":["distance"]},{"d":"bludge","f":1,"x":true,"a":["bludge"]},{"d":"muse","f":1,"x":false,"a":["muse"]},{"d":"antagonize","f":1,"x":false,"a":["antagonize"]},{"d":"saunter","f":1,"x":false,"a":["saunter"]},{"d":"launch","f":1,"x":false,"a":["launch"]},{"d":"like","f":1,"x":false,"a":["like"]},{"d":"pace","f":1,"x":false,"a":["pace"]},{"d":"slobber","f":1,"x":false,"a":["slobber"]},{"d":"stroll","f":1,"x":false,"a":["stroll"]},{"d":"awaken","f":1,"x":false,"a":["awaken"]},{"d":"chillax","f":1,"x":false,"a":["chillax"]},{"d":"hang","f":1,"x":false,"a":["hang"]},{"d":"sashay","f":1,"x":false,"a":["sashay"]},{"d":"advertise","f":1,"x":false,"a":["advertise"]},{"d":"smear","f":1,"x":false,"a":["smear"]},{"d":"sunbake","f":1,"x":false,"a":["sunbake"]},{"d":"function","f":1,"x":false,"a":["function"]},{"d":"gulp","f":1,"x":false,"a":["gulp"]},{"d":"sweat","f":1,"x":false,"a":["sweat"]},{"d":"flirt","f":1,"x":false,"a":["flirt"]},{"d":"laze","f":1,"x":false,"a":["laze"]},{"d":"sizzle","f":1,"x":false,"a":["sizzle"]},{"d":"cross","f":1,"x":false,"a":["cross"]},{"d":"loiter","f":1,"x":false,"a":["loiter"]},{"d":"observe","f":1,"x":false,"a":["observe"]},{"d":"skive","f":1,"x":false,"a":["skive"]},{"d":"zap","f":1,"x":false,"a":["zap"]},{"d":"jaywalk","f":1,"x":false,"a":["jaywalk"]},{"d":"twerk","f":1,"x":true,"a":["twerk"]},{"d":"communicate","f":1,"x":false,"a":["communicate"]},{"d":"yoga","f":1,"x":false,"a":["yoga"]},{"d":"bumble","f":1,"x":false,"a":["bumble"]},{"d":"meet","f":1,"x":false,"a":["meet"]},{"d":"microwave","f":1,"x":false,"a":["microwave"]},{"d":"shunned","f":1,"x":false,"a":["shunned"]},{"d":"blog","f":1,"x":false,"a":["blog"]},{"d":"stammer","f":1,"x":false,"a":["stammer"]},{"d":"smize","f":1,"x":false,"a":["smize"]},{"d":"slurp","f":1,"x":false,"a":["slurp"]},{"d":"splutter","f":1,"x":false,"a":["splutter"]},{"d":"unwind","f":1,"x":false,"a":["unwind"]},{"d":"gyrate","f":1,"x":true,"a":["gyrate"]},{"d":"jam","f":1,"x":false,"a":["jam"]},{"d":"squirm","f":1,"x":false,"a":["squirm"]},{"d":"dally","f":1,"x":false,"a":["dally"]},{"d":"stalk","f":1,"x":false,"a":["stalk"]},{"d":"guffaw","f":1,"x":false,"a":["guffaw"]},{"d":"taunt","f":1,"x":false,"a":["taunt"]},{"d":"cackle","f":1,"x":false,"a":["cackle"]},{"d":"have","f":1,"x":false,"a":["have"]},{"d":"sag","f":1,"x":false,"a":["sag"]},{"d":"wheeze","f":1,"x":false,"a":["wheeze"]},{"d":"bop","f":1,"x":false,"a":["bop"]},{"d":"consume","f":1,"x":false,"a":["consume"]},{"d":"floss","f":1,"x":false,"a":["floss"]},{"d":"nuke","f":1,"x":false,"a":["nuke"]},{"d":"categorize","f":1,"x":false,"a":["categorize"]},{"d":"chill","f":1,"x":false,"a":["chill"]},{"d":"fry","f":1,"x":false,"a":["fry"]},{"d":"overcome","f":1,"x":false,"a":["overcome"]},{"d":"snicker","f":1,"x":false,"a":["snicker"]},{"d":"snoop","f":1,"x":false,"a":["snoop"]},{"d":"washup","f":1,"x":false,"a":["washup"]},{"d":"feast","f":1,"x":false,"a":["feast"]},{"d":"dominate","f":1,"x":false,"a":["dominate"]},{"d":"collapse","f":1,"x":false,"a":["collapse"]},{"d":"muddle","f":1,"x":false,"a":["muddle"]},{"d":"yearn","f":1,"x":false,"a":["yearn"]},{"d":"mooch","f":1,"x":false,"a":["mooch"]},{"d":"glow","f":1,"x":false,"a":["glow"]},{"d":"groove","f":1,"x":false,"a":["groove"]},{"d":"perspire","f":1,"x":false,"a":["perspire"]},{"d":"blunder","f":1,"x":false,"a":["blunder"]},{"d":"plonk","f":1,"x":true,"a":["plonk"]},{"d":"mumble","f":1,"x":false,"a":["mumble"]},{"d":"avoided","f":1,"x":false,"a":["avoided"]},{"d":"hydrating","f":1,"x":false,"a":["hydrating"]},{"d":"desire","f":1,"x":false,"a":["desire"]},{"d":"replicate","f":1,"x":false,"a":["replicate"]},{"d":"veg","f":1,"x":false,"a":["veg"]},{"d":"crave","f":1,"x":false,"a":["crave"]},{"d":"click","f":1,"x":false,"a":["click"]},{"d":"scoff","f":1,"x":false,"a":["scoff"]},{"d":"splurge","f":1,"x":false,"a":["splurge"]},{"d":"swipe","f":1,"x":false,"a":["swipe"]},{"d":"jabber","f":1,"x":false,"a":["jabber"]},{"d":"tweak","f":1,"x":false,"a":["tweak"]},{"d":"whine","f":1,"x":false,"a":["whine"]},{"d":"zigzag","f":1,"x":false,"a":["zigzag"]},{"d":"annoy","f":1,"x":false,"a":["annoy"]},{"d":"conquer","f":1,"x":false,"a":["conquer"]},{"d":"sputter","f":1,"x":false,"a":["sputter"]},{"d":"adapt","f":1,"x":false,"a":["adapt"]},{"d":"wriggle","f":1,"x":false,"a":["wriggle"]},{"d":"gaze","f":1,"x":false,"a":["gaze"]},{"d":"trudge","f":1,"x":false,"a":["trudge"]},{"d":"breath","f":1,"x":false,"a":["breath"]},{"d":"pamper","f":1,"x":false,"a":["pamper"]},{"d":"slog","f":1,"x":false,"a":["slog"]},{"d":"babble","f":1,"x":false,"a":["babble"]},{"d":"chomp","f":1,"x":false,"a":["chomp"]},{"d":"gape","f":1,"x":false,"a":["gape"]},{"d":"market","f":1,"x":false,"a":["market"]},{"d":"jumble","f":1,"x":false,"a":["jumble"]},{"d":"moisturise","f":1,"x":false,"a":["moisturise"]},{"d":"tease","f":1,"x":false,"a":["tease"]},{"d":"treat","f":1,"x":false,"a":["treat"]},{"d":"gobble","f":1,"x":false,"a":["gobble"]},{"d":"nosh","f":1,"x":false,"a":["nosh"]},{"d":"dabble","f":1,"x":false,"a":["dabble"]},{"d":"hunch","f":1,"x":false,"a":["hunch"]},{"d":"slather","f":1,"x":false,"a":["slather"]},{"d":"booze","f":1,"x":false,"a":["booze"]},{"d":"fun","f":1,"x":false,"a":["fun"]},{"d":"worry","f":1,"x":false,"a":["worry"]},{"d":"beam","f":1,"x":false,"a":["beam"]},{"d":"gasp","f":1,"x":false,"a":["gasp"]},{"d":"bait","f":1,"x":false,"a":["bait"]},{"d":"coordinate","f":1,"x":false,"a":["coordinate"]},{"d":"flop","f":1,"x":false,"a":["flop"]}]}