{"l":[{"d":"Berg","f":249,"x":false,"a":["Berge","Berg","Gebirge","Berggipfel"]},{"d":"Schloss","f":201,"x":false,"a":["Schlösser","Schloss"]},{"d":"König","f":157,"x":false,"a":["Koenig","König"]},{"d":"Löwe","f":154,"x":false,"a":["Löwen","Löwe"]},{"d":"Meer","f":140,"x":false,"a":["Meer"]},{"d":"Sonnenuntergang","f":110,"x":false,"a":["Sonnenuntergang"]},{"d":"Krone","f":108,"x":false,"a":["Krone"]},{"d":"Penis","f":104,"x":true,"a":["Penis"]},{"d":"Königin","f":101,"x":false,"a":["Queen","Königin"]},{"d":"Ich","f":99,"x":false,"a":["Ich"]},{"d":"Katze","f":89,"x":false,"a":["Katzen","Katze"]},{"d":"Wasserfall","f":87,"x":false,"a":["Waterfall","Wasserfall","Wasserfälle","Wassefall"]},{"d":"Brüste","f":83,"x":true,"a":["Titten","Brüste"]},{"d":"Palast","f":72,"x":false,"a":["Palast"]},{"d":"Pferd","f":71,"x":false,"a":["Pferde","Pferd"]},{"d":"Sonnenaufgang","f":63,"x":false,"a":["Sonnenaufgang"]},{"d":"Burg","f":59,"x":false,"a":["Burgen","Burg"]},{"d":"Himmel","f":55,"x":false,"a":["Himmek","Himmel"]},{"d":"Hintern","f":55,"x":true,"a":["Arsch","Hintern"]},{"d":"Ozean","f":53,"x":false,"a":["Ozeanze","Ozean"]},{"d":"Hund","f":51,"x":false,"a":["Hund"]},{"d":"Haus","f":51,"x":false,"a":["Haus"]},{"d":"Eiffelturm","f":50,"x":false,"a":["Eifelturm","Eiffelturm","Eiffel"]},{"d":"Kot","f":50,"x":true,"a":["Kacke","Kot","Scheiße"]},{"d":"Pyramide","f":49,"x":false,"a":["Pyramiden","Pyramide"]},{"d":"Frau","f":48,"x":true,"a":["Frau"]},{"d":"Auto","f":45,"x":false,"a":["Auto"]},{"d":"Alpen","f":44,"x":false,"a":["Alpen"]},{"d":"Baum","f":44,"x":false,"a":["Bäume","Baum"]},{"d":"Thron","f":44,"x":false,"a":["Thron"]},{"d":"Mann","f":40,"x":false,"a":["Männer","Mann"]},{"d":"Adler","f":39,"x":false,"a":["Adler"]},{"d":"See","f":39,"x":false,"a":["See"]},{"d":"Tiger","f":39,"x":false,"a":["Tiger"]},{"d":"Wald","f":38,"x":false,"a":["Wälder","Wald"]},{"d":"Toilette","f":38,"x":false,"a":["Klo","Toilette"]},{"d":"Kirche","f":36,"x":false,"a":["Kirche"]},{"d":"Sonne","f":35,"x":false,"a":["Sonne"]},{"d":"Sterne","f":35,"x":false,"a":["Sterne"]},{"d":"Frauen","f":33,"x":false,"a":["Frauen"]},{"d":"Natur","f":32,"x":false,"a":["Natur"]},{"d":"Mond","f":32,"x":false,"a":["Mond"]},{"d":"Elefant","f":32,"x":false,"a":["Elefant"]},{"d":"Prinz","f":30,"x":false,"a":["Prinz"]},{"d":"Landschaft","f":30,"x":false,"a":["Landschaften","Landschaft"]},{"d":"Strand","f":30,"x":false,"a":["Strand"]},{"d":"Prinzessin","f":30,"x":false,"a":["Prinzessin"]},{"d":"Essen","f":30,"x":false,"a":["Essen"]},{"d":"Kind","f":30,"x":true,"a":["Kinder","Kind"]},{"d":"Gold","f":29,"x":false,"a":["Gold"]},{"d":"Fluss","f":29,"x":false,"a":["Fluss"]},{"d":"Wal","f":27,"x":false,"a":["Wal"]},{"d":"Turm","f":27,"x":false,"a":["Tower","Turm"]},{"d":"Statue","f":26,"x":false,"a":["Statuen","Statue"]},{"d":"Tier","f":26,"x":false,"a":["Tier"]},{"d":"Tiere","f":25,"x":false,"a":["Tiere"]},{"d":"Polarlicht","f":25,"x":false,"a":["Nordlichte","Polarlicht","Polarlichter","Nordlicht","Nordlichter"]},{"d":"Kaiser","f":25,"x":false,"a":["Kaiser"]},{"d":"Bier","f":23,"x":true,"a":["Bier"]},{"d":"Giraffe","f":21,"x":false,"a":["Giraffen","Giraffe"]},{"d":"Geld","f":20,"x":false,"a":["Geld"]},{"d":"Tempel","f":19,"x":false,"a":["Tempel"]},{"d":"Berlin","f":19,"x":false,"a":["Berlin"]},{"d":"Gemälde","f":19,"x":false,"a":["Gemälde"]},{"d":"Maus","f":19,"x":false,"a":["Maus"]},{"d":"Villa","f":18,"x":false,"a":["Villa"]},{"d":"Erde","f":17,"x":false,"a":["Erde"]},{"d":"Kutsche","f":17,"x":false,"a":["Kutsche"]},{"d":"Wow","f":17,"x":false,"a":["Wow"]},{"d":"Hirsch","f":17,"x":false,"a":["Hirsch"]},{"d":"Garten","f":17,"x":false,"a":["Garten"]},{"d":"Vogel","f":17,"x":false,"a":["Vogel"]},{"d":"Müll","f":17,"x":false,"a":["Müll"]},{"d":"Blume","f":17,"x":false,"a":["Blumen","Blume"]},{"d":"Flugzeug","f":16,"x":false,"a":["Flugzeug"]},{"d":"Kathedrale","f":16,"x":false,"a":["Kathedrale"]},{"d":"Schiff","f":16,"x":false,"a":["Schiff"]},{"d":"Wasser","f":16,"x":false,"a":["Wasser"]},{"d":"Zepter","f":15,"x":false,"a":["Zepter"]},{"d":"Mounteverest","f":15,"x":false,"a":["Mounteverest"]},{"d":"Du","f":15,"x":false,"a":["Du"]},{"d":"Sternenhimmel","f":15,"x":false,"a":["Sternenhimmel"]},{"d":"Wolken","f":15,"x":false,"a":["Wolken"]},{"d":"Grandcanyon","f":15,"x":false,"a":["Grandcanyon"]},{"d":"Einhorn","f":15,"x":false,"a":["Einhorn"]},{"d":"Panorama","f":14,"x":false,"a":["Panorama"]},{"d":"Paris","f":14,"x":false,"a":["Paris"]},{"d":"Pfau","f":14,"x":false,"a":["Pfau"]},{"d":"Kleid","f":14,"x":false,"a":["Kleid"]},{"d":"Stadt","f":14,"x":true,"a":["STADT","Stadt"]},{"d":"Bild","f":14,"x":false,"a":["Bild"]},{"d":"Wiese","f":14,"x":false,"a":["Wiese"]},{"d":"Juwel","f":14,"x":false,"a":["Juwelen","Juwel"]},{"d":"Wüste","f":13,"x":false,"a":["Wüste"]},{"d":"Gott","f":13,"x":false,"a":["Gott"]},{"d":"Baby","f":13,"x":false,"a":["Baby"]},{"d":"Planet","f":12,"x":false,"a":["Planeten","Planet"]},{"d":"Schwanz","f":12,"x":true,"a":["Schwanz"]},{"d":"Diamant","f":12,"x":false,"a":["Diamant"]},{"d":"Park","f":12,"x":false,"a":["Park"]},{"d":"Mensch","f":12,"x":false,"a":["Mensch"]},{"d":"Monalisa","f":12,"x":false,"a":["Monalisa"]},{"d":"Tajmahal","f":11,"x":false,"a":["Tajmahal"]},{"d":"Dom","f":11,"x":false,"a":["Dom"]},{"d":"Niagarafälle","f":11,"x":false,"a":["Niagarafälle"]},{"d":"Freundin","f":11,"x":false,"a":["Freundin"]},{"d":"Deutschland","f":11,"x":false,"a":["Deutschland"]},{"d":"Ritter","f":11,"x":false,"a":["Ritter"]},{"d":"Schule","f":11,"x":false,"a":["Schule"]},{"d":"Schmuck","f":11,"x":false,"a":["Schmuck"]},{"d":"Gipfel","f":10,"x":false,"a":["Gipfel"]},{"d":"Königlich","f":10,"x":false,"a":["Königlich"]},{"d":"Vulkan","f":10,"x":false,"a":["Vulkane","Vulkan"]},{"d":"Freiheitsstatue","f":10,"x":false,"a":["Freiheitsstatue"]},{"d":"Nachthimmel","f":10,"x":false,"a":["Nachthimmel"]},{"d":"Neuschwanstein","f":10,"x":false,"a":["Neuschwanstein"]},{"d":"Tal","f":10,"x":false,"a":["Tal"]},{"d":"Yacht","f":10,"x":false,"a":["Yacht"]},{"d":"Sphinx","f":10,"x":false,"a":["Sphinx"]},{"d":"Kunst","f":10,"x":false,"a":["Kunst"]},{"d":"Insel","f":10,"x":false,"a":["Insel"]},{"d":"Ratte","f":10,"x":false,"a":["Ratte"]},{"d":"Stuhl","f":10,"x":false,"a":["Stuhl"]},{"d":"Land","f":10,"x":false,"a":["Land"]},{"d":"Hai","f":10,"x":false,"a":["Hai"]},{"d":"Majestät","f":10,"x":false,"a":["Majestät"]},{"d":"Dreck","f":10,"x":false,"a":["Dreck"]},{"d":"Everest","f":9,"x":false,"a":["Everest"]},{"d":"Bär","f":9,"x":false,"a":["Bär"]},{"d":"Horizont","f":9,"x":false,"a":["Horizont"]},{"d":"Ausblick","f":9,"x":false,"a":["Ausblick"]},{"d":"Weltall","f":9,"x":false,"a":["Weltall"]},{"d":"Versailles","f":9,"x":false,"a":["Versaille","Versailles"]},{"d":"Japan","f":9,"x":false,"a":["Japan"]},{"d":"Atemberaubend","f":9,"x":false,"a":["Atemberaubend"]},{"d":"Schwan","f":9,"x":false,"a":["Schwan"]},{"d":"Kölnerdom","f":9,"x":false,"a":["Kölnerdom"]},{"d":"Bergpanorama","f":9,"x":false,"a":["Bergpanorama"]},{"d":"Straße","f":9,"x":false,"a":["Straße"]},{"d":"Gebäude","f":9,"x":false,"a":["Gebäude"]},{"d":"Museum","f":9,"x":false,"a":["Museum"]},{"d":"Hotel","f":9,"x":false,"a":["Hotel"]},{"d":"Pinguin","f":9,"x":false,"a":["Pinguin"]},{"d":"Nacktheit","f":9,"x":true,"a":["Nackt","Nacktheit"]},{"d":"Rakete","f":8,"x":false,"a":["Rakete"]},{"d":"Wundervoll","f":8,"x":false,"a":["Wundervoll"]},{"d":"Regenbogen","f":8,"x":false,"a":["Regenbogen"]},{"d":"Schlucht","f":8,"x":false,"a":["Schlucht"]},{"d":"Dschungel","f":8,"x":false,"a":["Dschungel"]},{"d":"Schönheit","f":8,"x":false,"a":["Schönheit"]},{"d":"Zugspitze","f":8,"x":false,"a":["Zugspitze"]},{"d":"Schuhe","f":8,"x":false,"a":["Schuhe"]},{"d":"Nacht","f":8,"x":false,"a":["Nacht"]},{"d":"Wolkenkratzer","f":8,"x":false,"a":["Wolkenkratzer"]},{"d":"Spiegel","f":8,"x":false,"a":["Spiegel"]},{"d":"Fuji","f":8,"x":false,"a":["Fuji"]},{"d":"Freund","f":8,"x":false,"a":["Freund"]},{"d":"Boot","f":8,"x":false,"a":["Boot"]},{"d":"Feld","f":8,"x":true,"a":["Felder","Feld"]},{"d":"Mauer","f":8,"x":false,"a":["Mauer"]},{"d":"Kotze","f":8,"x":false,"a":["Kotze"]},{"d":"Burjkhalifa","f":8,"x":false,"a":["Burjkhalifa"]},{"d":"G","f":8,"x":false,"a":["G"]},{"d":"Wale","f":7,"x":false,"a":["Wale"]},{"d":"Hunde","f":7,"x":false,"a":["Hunde"]},{"d":"Aussicht","f":7,"x":false,"a":["Aussicht"]},{"d":"Geburt","f":7,"x":false,"a":["Geburt"]},{"d":"Spiegelbild","f":7,"x":false,"a":["Spiegelbild"]},{"d":"Erhaben","f":7,"x":false,"a":["Erhaben"]},{"d":"Reh","f":7,"x":false,"a":["Reh"]},{"d":"China","f":7,"x":false,"a":["China"]},{"d":"Jaguar","f":6,"x":false,"a":["Jaguar"]},{"d":"Bett","f":6,"x":false,"a":["Bett"]},{"d":"Canyon","f":6,"x":false,"a":["Canyon"]},{"d":"Himalaya","f":6,"x":false,"a":["Himalaya"]},{"d":"Stadion","f":6,"x":false,"a":["Stadion"]},{"d":"Apfel","f":6,"x":false,"a":["Apfel"]},{"d":"Wolf","f":6,"x":false,"a":["Wolf"]},{"d":"Nilpferd","f":6,"x":false,"a":["Nilpferd"]},{"d":"Buckinghampalace","f":5,"x":false,"a":["Buckinghampalace"]},{"d":"Gletscher","f":5,"x":false,"a":["Gletscher"]},{"d":"Welt","f":5,"x":false,"a":["Welt"]},{"d":"Regenwald","f":5,"x":false,"a":["Regenwald"]},{"d":"Döner","f":5,"x":false,"a":["Döner"]},{"d":"Amazonas","f":5,"x":false,"a":["Amazonas"]},{"d":"Bayern","f":5,"x":false,"a":["Bayern"]},{"d":"Savanne","f":5,"x":false,"a":["Savanne"]},{"d":"Wien","f":4,"x":false,"a":["Wien"]},{"d":"Vatikan","f":4,"x":false,"a":["Vatikan"]},{"d":"Leuchtturm","f":4,"x":false,"a":["Leuchtturm"]},{"d":"Louvre","f":4,"x":false,"a":["Louvre"]},{"d":"Notredame","f":4,"x":false,"a":["Notredame"]},{"d":"Matterhorn","f":4,"x":false,"a":["Matterhorn"]},{"d":"Hafen","f":4,"x":false,"a":["Hafen"]},{"d":"Denkmal","f":4,"x":false,"a":["Denkmal"]},{"d":"Charles","f":4,"x":false,"a":["Charles"]},{"d":"Sydney","f":4,"x":false,"a":["Sydney"]},{"d":"Majestätisch","f":4,"x":false,"a":["Majestätisch"]},{"d":"Rasen","f":4,"x":false,"a":["Rasen"]},{"d":"Hochzeit","f":4,"x":false,"a":["Hochzeit"]},{"d":"Kleider","f":4,"x":false,"a":["Kleider"]},{"d":"Anzug","f":4,"x":false,"a":["Anzug"]},{"d":"Reichstag","f":4,"x":false,"a":["Reichstag"]},{"d":"Umhang","f":4,"x":false,"a":["Umhang"]},{"d":"Asien","f":4,"x":false,"a":["Asien"]},{"d":"Flagge","f":4,"x":false,"a":["Flagge"]},{"d":"Aurora","f":3,"x":false,"a":["Aurora"]},{"d":"Grandios","f":3,"x":false,"a":["Grandious","Grandios"]},{"d":"King","f":3,"x":false,"a":["King"]},{"d":"Bergsee","f":3,"x":false,"a":["Bergsee"]},{"d":"Geil","f":3,"x":false,"a":["Geil"]},{"d":"Präsident","f":3,"x":false,"a":["Präsident"]},{"d":"Blumenwiese","f":3,"x":false,"a":["Blumenwiese"]},{"d":"Limousine","f":3,"x":false,"a":["Limousine"]},{"d":"Skyline","f":3,"x":false,"a":["Skyline"]},{"d":"Kronjuwelen","f":3,"x":false,"a":["Kronjuwelen"]},{"d":"Klippe","f":3,"x":false,"a":["Cliff","Klippe"]},{"d":"Hut","f":3,"x":false,"a":["Hut"]},{"d":"Royal","f":3,"x":false,"a":["Royal"]},{"d":"Königspalast","f":3,"x":false,"a":["Königspalast"]},{"d":"Handschuhe","f":3,"x":false,"a":["Handschuhe"]},{"d":"Lasvegas","f":3,"x":false,"a":["Lasvegas"]},{"d":"Niagara","f":3,"x":false,"a":["Niagara"]},{"d":"Wunderbar","f":3,"x":false,"a":["Wunderbar"]},{"d":"Ruinen","f":3,"x":false,"a":["Ruinen"]},{"d":"Blauwal","f":2,"x":false,"a":["Blauwal"]},{"d":"Thronsaal","f":2,"x":false,"a":["Thronsaal"]},{"d":"Erscheinung","f":2,"x":false,"a":["Erscheinung"]},{"d":"Welle","f":2,"x":false,"a":["Welle"]},{"d":"Seoul","f":2,"x":false,"a":["Seoul"]},{"d":"Augenweide","f":2,"x":false,"a":["Augenweide"]},{"d":"Gebirgskette","f":2,"x":false,"a":["Gebirgskette"]},{"d":"Paläste","f":2,"x":false,"a":["Paläste"]},{"d":"Ludwig","f":2,"x":false,"a":["Ludwig"]},{"d":"Sahara","f":2,"x":false,"a":["Sahara"]},{"d":"Braut","f":2,"x":false,"a":["Braut"]},{"d":"Arktis","f":2,"x":false,"a":["Arktis"]},{"d":"Dresden","f":2,"x":false,"a":["Dresden"]},{"d":"Blick","f":2,"x":false,"a":["Blick"]},{"d":"Herrlich","f":2,"x":false,"a":["Herrlich"]},{"d":"Stonehenge","f":2,"x":false,"a":["Stonehenge"]},{"d":"Klippen","f":2,"x":false,"a":["Klippen"]},{"d":"Buckingham","f":2,"x":false,"a":["Buckingham"]},{"d":"Stolz","f":2,"x":false,"a":["Stolz"]},{"d":"Schatzkammer","f":2,"x":false,"a":["Schatzkammer"]},{"d":"Hammer","f":2,"x":false,"a":["Hammer"]},{"d":"Prachtvoll","f":2,"x":false,"a":["Prachtvoll"]},{"d":"Atlantik","f":2,"x":false,"a":["Atlantik"]},{"d":"Hochzeitstorte","f":2,"x":false,"a":["Hochzeitstorte"]},{"d":"Bergwelt","f":2,"x":false,"a":["Bergwelt"]},{"d":"Skulptur","f":2,"x":false,"a":["Skulptur"]},{"d":"Lichtung","f":2,"x":false,"a":["Lichtung"]},{"d":"Rehe","f":2,"x":false,"a":["Rehe"]},{"d":"Karibik","f":2,"x":false,"a":["Karibik"]},{"d":"Machupicchu","f":2,"x":false,"a":["Machupicchu"]},{"d":"Weide","f":2,"x":false,"a":["Weide"]},{"d":"Augenschmaus","f":2,"x":false,"a":["Augenschmaus"]},{"d":"Anmut","f":2,"x":false,"a":["Ahnmutig","Anmut"]},{"d":"Australien","f":2,"x":false,"a":["Australien"]},{"d":"Mexiko","f":2,"x":false,"a":["Mexiko"]},{"d":"Davinci","f":2,"x":false,"a":["Davini","Davinci"]},{"d":"Hochhausausblick","f":1,"x":false,"a":["Hochhausausblick"]},{"d":"Nudistin","f":1,"x":true,"a":["Nudistin"]},{"d":"Meereshorizont","f":1,"x":false,"a":["Meereshorizont"]},{"d":"Festmahl","f":1,"x":false,"a":["Festmahl"]},{"d":"Hofreitschule","f":1,"x":false,"a":["Hofreitschule"]},{"d":"Löwenfamilie","f":1,"x":false,"a":["Löwenfamilie"]},{"d":"Seeblick","f":1,"x":false,"a":["Seeblick"]},{"d":"Tropenwälder","f":1,"x":false,"a":["Tropenwälder"]},{"d":"Erleuchtend","f":1,"x":false,"a":["Erleuchtend"]},{"d":"Erfurchtgebietend","f":1,"x":false,"a":["Erfurchtgebietend"]},{"d":"Palisade","f":1,"x":false,"a":["Palisade"]},{"d":"Erhebend","f":1,"x":false,"a":["Erhebend"]},{"d":"Mittelmeer","f":1,"x":false,"a":["Mittelmeer"]},{"d":"Pferdeherde","f":1,"x":false,"a":["Pferdeherde"]},{"d":"Traumhaft","f":1,"x":false,"a":["Traumhaft"]},{"d":"Bergaussicht","f":1,"x":false,"a":["Bergaussicht"]},{"d":"Überwältigend","f":1,"x":false,"a":["Überwältigend"]},{"d":"Fujiyama","f":1,"x":false,"a":["Fujiyama"]},{"d":"Kappadokien","f":1,"x":false,"a":["Kappadokien"]},{"d":"Oase","f":1,"x":false,"a":["Oase"]},{"d":"Seelandschaft","f":1,"x":false,"a":["Seelandschaft"]},{"d":"Untertanen","f":1,"x":false,"a":["Untertanen"]},{"d":"Wildtiere","f":1,"x":false,"a":["Wildtiere"]},{"d":"Halskette","f":1,"x":false,"a":["Halskette"]},{"d":"Würdevoll","f":1,"x":false,"a":["Würdevoll"]},{"d":"Ansehnlich","f":1,"x":false,"a":["Ansehnlich"]},{"d":"Ehepartner","f":1,"x":true,"a":["Ehepartner"]},{"d":"Rheintal","f":1,"x":false,"a":["Rheintal"]},{"d":"Walchensee","f":1,"x":false,"a":["Walchensee"]},{"d":"Wölfe","f":1,"x":false,"a":["Wölfe"]},{"d":"Ballsaal","f":1,"x":false,"a":["Ballsaal"]},{"d":"Hinreissend","f":1,"x":false,"a":["Hinreissend"]},{"d":"Stadtpanorma","f":1,"x":false,"a":["Stadtpanorma"]},{"d":"Schlosspark","f":1,"x":false,"a":["Schlosspark"]},{"d":"Reizend","f":1,"x":false,"a":["Reizend"]},{"d":"Sonnenblumenfelder","f":1,"x":false,"a":["Sonnenblumenfelder"]},{"d":"Spektakel","f":1,"x":false,"a":["Spektakel"]},{"d":"Pantheon","f":1,"x":false,"a":["Pantheon"]},{"d":"Marmorskulptur","f":1,"x":false,"a":["Marmorskulptur"]},{"d":"Goldschmuck","f":1,"x":false,"a":["Goldschmuck"]},{"d":"Sauerland","f":1,"x":false,"a":["Sauerland"]},{"d":"Bergkulisse","f":1,"x":false,"a":["Bergkulisse"]},{"d":"Ikonisch","f":1,"x":false,"a":["Ikonisch"]},{"d":"Respektvoll","f":1,"x":false,"a":["Respektvoll"]},{"d":"Gutaussehend","f":1,"x":false,"a":["Gutaussehend"]},{"d":"Tafelberg","f":1,"x":false,"a":["Tafelberg"]},{"d":"Urwald","f":1,"x":false,"a":["Urwald"]},{"d":"Waliserflagge","f":1,"x":false,"a":["Waliserflagge"]},{"d":"Episch","f":1,"x":false,"a":["Episch"]},{"d":"Lhasa","f":1,"x":false,"a":["Lhasa"]},{"d":"Montblanc","f":1,"x":false,"a":["Montblanc"]},{"d":"Hermitage","f":1,"x":false,"a":["Hermitage"]},{"d":"Riviera","f":1,"x":false,"a":["Riviera"]},{"d":"Tropfsteinhöhle","f":1,"x":false,"a":["Tropfsteinhöhle"]},{"d":"Elche","f":1,"x":false,"a":["Elche"]},{"d":"Mächtig","f":1,"x":false,"a":["Mächtig"]},{"d":"Werraschleife","f":1,"x":false,"a":["Werraschleife"]},{"d":"Athletinnen","f":1,"x":false,"a":["Athletinnen"]},{"d":"Unglaublich","f":1,"x":false,"a":["Unglaublich"]},{"d":"Kalksteinfelsen","f":1,"x":false,"a":["Kalksteinfelsen"]},{"d":"Lamborghini","f":1,"x":false,"a":["Lamborghini"]},{"d":"Winterlandschaft","f":1,"x":false,"a":["Winterlandschaft"]},{"d":"Raubtiere","f":1,"x":false,"a":["Raubtiere"]},{"d":"Seen","f":1,"x":false,"a":["Seen"]},{"d":"Adelig","f":1,"x":false,"a":["Adelig"]},{"d":"Morgensonne","f":1,"x":false,"a":["Morgensonne"]},{"d":"Treppenhaus","f":1,"x":false,"a":["Treppenhaus"]},{"d":"Colloseum","f":1,"x":false,"a":["Colloseum"]},{"d":"Kilimandscharo","f":1,"x":false,"a":["Kilimandscharo"]},{"d":"Meeresspiegel","f":1,"x":false,"a":["Meeresspiegel"]},{"d":"Eindrucksvoll","f":1,"x":false,"a":["Eindrucksvoll"]},{"d":"Stattlich","f":1,"x":false,"a":["Stattlich"]},{"d":"Gärten","f":1,"x":false,"a":["Gärten"]},{"d":"Sichtschneise","f":1,"x":false,"a":["Sichtschneise"]},{"d":"Sonnenuntergänge","f":1,"x":false,"a":["Sonnenuntergänge"]},{"d":"Zionnationalpark","f":1,"x":false,"a":["Zionnationalpark"]},{"d":"Feierlich","f":1,"x":false,"a":["Feierlich"]},{"d":"Grossstadt","f":1,"x":false,"a":["Grossstadt"]},{"d":"Queenelisabeth","f":1,"x":false,"a":["Queenelisabeth"]},{"d":"Sunrise","f":1,"x":false,"a":["Sunrise"]},{"d":"Akropolis","f":1,"x":false,"a":["Akropolis"]},{"d":"Hochgebirge","f":1,"x":false,"a":["Hochgebirge"]},{"d":"Prächtig","f":1,"x":false,"a":["Prächtig"]},{"d":"Thor","f":1,"x":false,"a":["Thor"]},{"d":"Empore","f":1,"x":false,"a":["Empore"]},{"d":"Hammerhaischwarm","f":1,"x":false,"a":["Hammerhaischwarm"]},{"d":"Rheinfall","f":1,"x":false,"a":["Rheinfall"]},{"d":"Bergspitze","f":1,"x":false,"a":["Bergspitze"]},{"d":"Reitpferd","f":1,"x":false,"a":["Reitpferd"]},{"d":"Wolfsrudel","f":1,"x":false,"a":["Wolfsrudel"]},{"d":"Hongkong","f":1,"x":false,"a":["Hongkong"]},{"d":"Grauwal","f":1,"x":false,"a":["Grauwal"]},{"d":"Wucht","f":1,"x":false,"a":["Wucht"]},{"d":"Attraktiv","f":1,"x":false,"a":["Attraktiv"]},{"d":"Kleidung","f":1,"x":false,"a":["Kleidung"]},{"d":"Tempelruinen","f":1,"x":false,"a":["Tempelruinen"]},{"d":"Wahl","f":1,"x":false,"a":["Wahl"]},{"d":"Eindruck","f":1,"x":false,"a":["Eindruck"]},{"d":"Gitarren","f":1,"x":false,"a":["Gitarren"]},{"d":"Jerusalem","f":1,"x":false,"a":["Jerusalem"]},{"d":"Meerblick","f":1,"x":false,"a":["Meerblick"]},{"d":"hügel","f":1,"x":false,"a":["hügel"]},{"d":"Kabine","f":1,"x":false,"a":["Kabine"]},{"d":"Reise","f":1,"x":false,"a":["Reise"]},{"d":"Höhen","f":1,"x":false,"a":["Höhen"]},{"d":"abheben","f":1,"x":false,"a":["abheben"]},{"d":"Karriere","f":1,"x":false,"a":["Karriere"]},{"d":"NewYork","f":1,"x":false,"a":["NewYork"]},{"d":"Lunge","f":1,"x":false,"a":["Lunge"]},{"d":"Eisberg","f":1,"x":false,"a":["Eisberg"]},{"d":"Malerei","f":1,"x":false,"a":["Malerei"]},{"d":"Raum","f":1,"x":false,"a":["Raum"]},{"d":"Mexico","f":1,"x":false,"a":["Mexico"]},{"d":"Spain","f":1,"x":false,"a":["Spain"]},{"d":"Portugal","f":1,"x":false,"a":["Portugal"]}]}