{"l":[{"d":"faca","f":108,"x":false,"a":["facas","faca"]},{"d":"tesoura","f":55,"x":false,"a":["tesouras","tesoura"]},{"d":"computador","f":44,"x":false,"a":["computador"]},{"d":"carro","f":43,"x":false,"a":["carros","carro"]},{"d":"arma","f":39,"x":true,"a":["armas","arma"]},{"d":"violão","f":39,"x":false,"a":["violão"]},{"d":"bisturi","f":36,"x":false,"a":["bisturi"]},{"d":"furadeira","f":33,"x":false,"a":["furadeira"]},{"d":"celular","f":29,"x":false,"a":["celulares","celular"]},{"d":"martelo","f":27,"x":false,"a":["martelo"]},{"d":"violino","f":26,"x":false,"a":["violino"]},{"d":"pincel","f":23,"x":false,"a":["pincel"]},{"d":"agulha","f":22,"x":false,"a":["agulha"]},{"d":"piano","f":22,"x":false,"a":["piano"]},{"d":"espada","f":18,"x":true,"a":["espada"]},{"d":"arco","f":17,"x":false,"a":["arco"]},{"d":"skate","f":16,"x":false,"a":["skate"]},{"d":"guitarra","f":15,"x":false,"a":["guitarra"]},{"d":"serra","f":14,"x":false,"a":["serra"]},{"d":"lápis","f":14,"x":false,"a":["lápis"]},{"d":"instrumento","f":14,"x":false,"a":["instrumentos","instrumento","instrumentomusical"]},{"d":"moto","f":11,"x":false,"a":["moto"]},{"d":"panela","f":11,"x":false,"a":["paneladepressão","panela","panelas"]},{"d":"drone","f":11,"x":false,"a":["drone"]},{"d":"ferramenta","f":10,"x":false,"a":["ferramentas","ferramenta"]},{"d":"motosserra","f":10,"x":false,"a":["motosseras","motosserra"]},{"d":"bicicleta","f":10,"x":false,"a":["bicicleta"]},{"d":"revólver","f":10,"x":true,"a":["revolver","revólver"]},{"d":"bola","f":9,"x":false,"a":["bolas","bola"]},{"d":"avião","f":9,"x":false,"a":["avião"]},{"d":"alicate","f":9,"x":false,"a":["alicate"]},{"d":"teclado","f":8,"x":false,"a":["teclado"]},{"d":"maçarico","f":6,"x":false,"a":["maçarico"]},{"d":"pistola","f":6,"x":true,"a":["pistolas","pistola"]},{"d":"bateria","f":6,"x":false,"a":["bateria"]},{"d":"fogão","f":6,"x":false,"a":["fogão"]},{"d":"machado","f":6,"x":false,"a":["machado"]},{"d":"britadeira","f":5,"x":false,"a":["britadeira"]},{"d":"navalha","f":5,"x":false,"a":["navalha"]},{"d":"câmera","f":5,"x":false,"a":["câmera"]},{"d":"cozinhar","f":5,"x":false,"a":["cozinhar"]},{"d":"serrote","f":5,"x":false,"a":["serrote"]},{"d":"flauta","f":4,"x":false,"a":["flauta"]},{"d":"secador","f":4,"x":false,"a":["secadordecabelo","secador"]},{"d":"caneta","f":4,"x":false,"a":["caneta"]},{"d":"batedeira","f":4,"x":false,"a":["batedeira"]},{"d":"barbeador","f":4,"x":false,"a":["barbeador"]},{"d":"notebook","f":4,"x":false,"a":["notebook"]},{"d":"fogo","f":4,"x":false,"a":["fogo"]},{"d":"forno","f":4,"x":false,"a":["forno"]},{"d":"patins","f":4,"x":false,"a":["patins"]},{"d":"videogame","f":4,"x":false,"a":["videogame"]},{"d":"chave","f":4,"x":false,"a":["chave"]},{"d":"motocicleta","f":4,"x":false,"a":["motocicleta"]},{"d":"facão","f":4,"x":false,"a":["facão"]},{"d":"seringa","f":3,"x":false,"a":["seringa"]},{"d":"enxada","f":3,"x":false,"a":["inchada","enxada","inchadas"]},{"d":"estilete","f":3,"x":false,"a":["estilete"]},{"d":"calculadora","f":3,"x":false,"a":["calculadora"]},{"d":"saxofone","f":3,"x":false,"a":["saxofone"]},{"d":"volante","f":3,"x":false,"a":["volante"]},{"d":"gaita","f":3,"x":false,"a":["gaita"]},{"d":"frigideira","f":3,"x":false,"a":["frigideira"]},{"d":"máquinas","f":3,"x":false,"a":["máquinas"]},{"d":"caminhão","f":3,"x":false,"a":["caminhões","caminhão"]},{"d":"cubomágico","f":3,"x":false,"a":["cubomágico"]},{"d":"empilhadeira","f":3,"x":false,"a":["empilhadeira"]},{"d":"estetoscópio","f":3,"x":false,"a":["estetoscópio"]},{"d":"abridor","f":3,"x":false,"a":["abridor"]},{"d":"ralador","f":3,"x":false,"a":["ralador"]},{"d":"pinça","f":3,"x":false,"a":["pinça"]},{"d":"churrasqueira","f":3,"x":false,"a":["churrasqueira"]},{"d":"fuzil","f":3,"x":true,"a":["fuzil"]},{"d":"microscópio","f":3,"x":false,"a":["microscópio"]},{"d":"flecha","f":3,"x":true,"a":["flecha"]},{"d":"talheres","f":2,"x":false,"a":["talher","talheres"]},{"d":"desenhar","f":2,"x":false,"a":["desenhar"]},{"d":"betoneira","f":2,"x":false,"a":["betoneira"]},{"d":"dildo","f":2,"x":true,"a":["dildo"]},{"d":"aspirador","f":2,"x":false,"a":["aspirador"]},{"d":"dardos","f":2,"x":false,"a":["dardos"]},{"d":"game","f":2,"x":false,"a":["game"]},{"d":"harpa","f":2,"x":false,"a":["harpa"]},{"d":"isqueiro","f":2,"x":false,"a":["isqueiro"]},{"d":"injeção","f":2,"x":false,"a":["injeção"]},{"d":"maquita","f":2,"x":false,"a":["maquita"]},{"d":"xadrez","f":2,"x":false,"a":["xadrez"]},{"d":"dirigir","f":2,"x":false,"a":["dirigir"]},{"d":"controle","f":2,"x":false,"a":["controle"]},{"d":"chapinha","f":2,"x":false,"a":["chapinha"]},{"d":"vibrador","f":2,"x":true,"a":["vibrador"]},{"d":"prancha","f":2,"x":false,"a":["prancha"]},{"d":"canhão","f":2,"x":true,"a":["canhão"]},{"d":"trator","f":2,"x":false,"a":["tratores","trator"]},{"d":"foguete","f":2,"x":false,"a":["foguetes","foguete"]},{"d":"tablet","f":2,"x":false,"a":["tablet"]},{"d":"raquete","f":2,"x":false,"a":["raquete"]},{"d":"televisão","f":2,"x":false,"a":["televisão"]},{"d":"computadores","f":2,"x":false,"a":["pc","computadores"]},{"d":"compasso","f":2,"x":false,"a":["compasso"]},{"d":"pilotar","f":2,"x":false,"a":["pilotar"]},{"d":"baqueta","f":2,"x":false,"a":["baquetas","baqueta"]},{"d":"jogar","f":2,"x":false,"a":["jogar"]},{"d":"corda","f":2,"x":false,"a":["corda"]},{"d":"descascador","f":2,"x":false,"a":["descascadorcenoura","descascador"]},{"d":"cantar","f":2,"x":false,"a":["cantar"]},{"d":"relógio","f":2,"x":false,"a":["relógio"]},{"d":"cafeteira","f":2,"x":false,"a":["cafeteira"]},{"d":"livro","f":2,"x":false,"a":["livro"]},{"d":"impressora","f":2,"x":false,"a":["impressora"]},{"d":"régua","f":1,"x":false,"a":["régua"]},{"d":"sinuca","f":1,"x":false,"a":["sinuca"]},{"d":"vara","f":1,"x":false,"a":["vara"]},{"d":"delineador","f":1,"x":false,"a":["delineador"]},{"d":"ferrodesolda","f":1,"x":false,"a":["ferrodesolda"]},{"d":"torno","f":1,"x":false,"a":["torno"]},{"d":"eletrônicos","f":1,"x":false,"a":["eletrônicos"]},{"d":"desenvolver","f":1,"x":false,"a":["desenvolver"]},{"d":"sacarolha","f":1,"x":false,"a":["sacarolha"]},{"d":"mouse","f":1,"x":false,"a":["mouse"]},{"d":"termômetro","f":1,"x":false,"a":["termômetro"]},{"d":"tomógrafo","f":1,"x":false,"a":["tomógrafo"]},{"d":"drink","f":1,"x":true,"a":["drink"]},{"d":"sábado","f":1,"x":false,"a":["sábado"]},{"d":"malabares","f":1,"x":false,"a":["malabares"]},{"d":"tecnologia","f":1,"x":false,"a":["tecnologia"]},{"d":"cola","f":1,"x":false,"a":["cola"]},{"d":"peão","f":1,"x":false,"a":["peão"]},{"d":"drones","f":1,"x":false,"a":["drones"]},{"d":"hashi","f":1,"x":false,"a":["hashi"]},{"d":"canoa","f":1,"x":false,"a":["canoa"]},{"d":"retroescavadeira","f":1,"x":false,"a":["retroescavadeira"]},{"d":"giz","f":1,"x":false,"a":["giz"]},{"d":"laser","f":1,"x":false,"a":["laser"]},{"d":"complexo","f":1,"x":false,"a":["complexo"]},{"d":"cotonete","f":1,"x":false,"a":["cotonete"]},{"d":"desafio","f":1,"x":false,"a":["desafio"]},{"d":"monociclo","f":1,"x":false,"a":["monociclo"]},{"d":"pião","f":1,"x":false,"a":["pião"]},{"d":"cadeado","f":1,"x":false,"a":["cadeado"]},{"d":"rímel","f":1,"x":false,"a":["rímel"]},{"d":"preciso","f":1,"x":false,"a":["preciso"]},{"d":"copiadora","f":1,"x":false,"a":["copiadora"]},{"d":"teoria","f":1,"x":false,"a":["teoria"]},{"d":"gilete","f":1,"x":false,"a":["gilete"]},{"d":"pranchadecabelo","f":1,"x":false,"a":["pranchadecabelo"]},{"d":"motocross","f":1,"x":false,"a":["motocross"]},{"d":"vôlei","f":1,"x":false,"a":["vôlei"]},{"d":"voz","f":1,"x":false,"a":["voz"]},{"d":"arte","f":1,"x":false,"a":["arte"]},{"d":"harry","f":1,"x":false,"a":["harry"]},{"d":"hoje","f":1,"x":false,"a":["hoje"]},{"d":"automóvel","f":1,"x":false,"a":["automóvel"]},{"d":"leitor","f":1,"x":false,"a":["leitor"]},{"d":"surfe","f":1,"x":false,"a":["surfe"]},{"d":"brinco","f":1,"x":false,"a":["brinco"]},{"d":"serradeira","f":1,"x":false,"a":["serradeira"]},{"d":"telescópio","f":1,"x":false,"a":["telescópio"]},{"d":"agilidade","f":1,"x":false,"a":["agilidade"]},{"d":"martelete","f":1,"x":false,"a":["martelete"]},{"d":"veículos","f":1,"x":false,"a":["veículos"]},{"d":"fósforo","f":1,"x":false,"a":["fósforo"]},{"d":"máquinafotográfica","f":1,"x":false,"a":["máquinafotográfica"]},{"d":"compositor","f":1,"x":false,"a":["compositor"]},{"d":"coqueteleira","f":1,"x":true,"a":["coqueteleira"]},{"d":"pipeta","f":1,"x":false,"a":["pipeta"]},{"d":"tiktok","f":1,"x":false,"a":["tiktok"]},{"d":"apontador","f":1,"x":false,"a":["apontador"]},{"d":"esmeriladeira","f":1,"x":false,"a":["esmeriladeira"]},{"d":"microdestilador","f":1,"x":false,"a":["microdestilador"]},{"d":"conversa","f":1,"x":false,"a":["conversa"]},{"d":"lixadeira","f":1,"x":false,"a":["lixadeira"]},{"d":"pênalti","f":1,"x":false,"a":["pênalti"]},{"d":"dançar","f":1,"x":false,"a":["dançar"]},{"d":"hóquei","f":1,"x":false,"a":["hóquei"]},{"d":"escultura","f":1,"x":false,"a":["escultura"]},{"d":"zarabatana","f":1,"x":true,"a":["zarabatana"]},{"d":"espingarda","f":1,"x":true,"a":["espingarda"]},{"d":"osciloscópio","f":1,"x":false,"a":["osciloscópio"]},{"d":"serraelétrica","f":1,"x":false,"a":["serraelétrica"]},{"d":"tear","f":1,"x":false,"a":["tear"]},{"d":"espectrômetro","f":1,"x":false,"a":["espectrômetro"]},{"d":"densímetro","f":1,"x":false,"a":["densímetro"]},{"d":"handebol","f":1,"x":false,"a":["handebol"]},{"d":"motor","f":1,"x":false,"a":["motor"]},{"d":"paquímetro","f":1,"x":false,"a":["paquímetro"]},{"d":"bumerangue","f":1,"x":false,"a":["bumerangue"]},{"d":"estanhador","f":1,"x":false,"a":["estanhador"]},{"d":"bússola","f":1,"x":false,"a":["bússola"]},{"d":"lixa","f":1,"x":false,"a":["lixa"]},{"d":"fiodental","f":1,"x":false,"a":["fiodental"]},{"d":"fole","f":1,"x":false,"a":["fole"]},{"d":"pinto","f":1,"x":true,"a":["pinto"]},{"d":"pipa","f":1,"x":false,"a":["pipa"]},{"d":"tática","f":1,"x":false,"a":["tática"]},{"d":"assistir","f":1,"x":false,"a":["assistir"]},{"d":"pinceis","f":1,"x":false,"a":["pinceis"]},{"d":"veículo","f":1,"x":false,"a":["veículo"]},{"d":"mágica","f":1,"x":false,"a":["mágica"]},{"d":"curve","f":1,"x":false,"a":["curve"]},{"d":"aprender","f":1,"x":false,"a":["aprender"]},{"d":"amolador","f":1,"x":false,"a":["amolador"]},{"d":"laminas","f":1,"x":false,"a":["laminas"]},{"d":"futebol","f":1,"x":false,"a":["futebol"]},{"d":"gasolina","f":1,"x":false,"a":["gasolina"]},{"d":"ipad","f":1,"x":false,"a":["ipad"]},{"d":"concluir","f":1,"x":false,"a":["concluir"]},{"d":"laptop","f":1,"x":false,"a":["laptop"]},{"d":"garrafa","f":1,"x":false,"a":["garrafa"]},{"d":"laço","f":1,"x":false,"a":["laço"]},{"d":"blocos","f":1,"x":false,"a":["blocos"]},{"d":"formão","f":1,"x":false,"a":["formão"]},{"d":"praticidade","f":1,"x":false,"a":["praticidade"]},{"d":"ioiô","f":1,"x":false,"a":["ioiô"]},{"d":"rifle","f":1,"x":true,"a":["rifle"]},{"d":"canivete","f":1,"x":false,"a":["canivetes","canivete"]},{"d":"judo","f":1,"x":false,"a":["judo"]},{"d":"amanhã","f":1,"x":false,"a":["amanhã"]},{"d":"satélite","f":1,"x":false,"a":["satélite"]},{"d":"cérebro","f":1,"x":false,"a":["cérebro"]},{"d":"agulhas","f":1,"x":false,"a":["agulhas"]},{"d":"especializado","f":1,"x":false,"a":["especializado"]},{"d":"chaira","f":1,"x":false,"a":["chaira"]}]}